neural_cherche
