Metadata-Version: 2.1
Name: neural_cherche
Version: 1.4.1
Summary: Sparse Embeddings for Neural Search.
Home-page: https://github.com/raphaelsty/neural-cherche
Download-URL: https://github.com/user/neural-cherche/archive/v_01.tar.gz
Author: Raphael Sourty
Author-email: raphael.sourty@gmail.com
Keywords: neural search,information retrieval,semantic search,SparseEmbed,Google Research,Splade,Stanford,ColBERT
Classifier: Programming Language :: Python :: 3
Classifier: License :: OSI Approved :: MIT License
Classifier: Operating System :: OS Independent
Requires-Python: >=3.6
License-File: LICENSE
Requires-Dist: torch>=1.13
Requires-Dist: tqdm>=4.66
Requires-Dist: transformers>=4.34.0
Requires-Dist: lenlp>=1.1.1
Requires-Dist: scikit-learn>=1.5.0
Provides-Extra: eval
Requires-Dist: torch>=1.13; extra == "eval"
Requires-Dist: tqdm>=4.66; extra == "eval"
Requires-Dist: transformers>=4.34.0; extra == "eval"
Requires-Dist: lenlp>=1.1.1; extra == "eval"
Requires-Dist: scikit-learn>=1.5.0; extra == "eval"
Requires-Dist: ranx>=0.3.16; extra == "eval"
Requires-Dist: beir>=2.0.0; extra == "eval"
Provides-Extra: dev
Requires-Dist: torch>=1.13; extra == "dev"
Requires-Dist: tqdm>=4.66; extra == "dev"
Requires-Dist: transformers>=4.34.0; extra == "dev"
Requires-Dist: lenlp>=1.1.1; extra == "dev"
Requires-Dist: scikit-learn>=1.5.0; extra == "dev"
Requires-Dist: ranx>=0.3.16; extra == "dev"
Requires-Dist: beir>=2.0.0; extra == "dev"
Requires-Dist: mkdocs-material==9.2.8; extra == "dev"
Requires-Dist: mkdocs-awesome-pages-plugin==2.9.2; extra == "dev"
Requires-Dist: mkdocs-jupyter==0.24.7; extra == "dev"
